{
  "patricia-d'amore-usds": [
    {
      "interviewType": "TQ1",
      "candidateName": "Romaine Fritsch",
      "talentRep": "joey-butta",
      "hidden": true,
      "startTime": 1652395500,
      "friendlyStartTime": "5/12/2022, 6:45:00 PM"
    },
    {
      "interviewType": "TQ1",
      "candidateName": "Garett Becker",
      "talentRep": "tali-runs",
      "hidden": false,
      "startTime": 1653000300,
      "friendlyStartTime": "5/19/2022, 6:45:00 PM"
    },
    {
      "interviewType": "TQ2",
      "candidateName": "Aileen Rice",
      "talentRep": "lan-party-man",
      "hidden": false,
      "startTime": 1653605100,
      "friendlyStartTime": "5/26/2022, 6:45:00 PM"
    },
    {
      "interviewType": "TQ1",
      "candidateName": "Zane Hahn",
      "talentRep": "joey-butta",
      "hidden": false,
      "startTime": 1654209900,
      "friendlyStartTime": "6/2/2022, 6:45:00 PM"
    },
    {
      "interviewType": "TQ2",
      "candidateName": "Katarina Maggio",
      "talentRep": "hieu-hieu",
      "hidden": false,
      "startTime": 1654814700,
      "friendlyStartTime": "6/9/2022, 6:45:00 PM"
    }
  ],
  "destiny-schuppe-usds": [
    {
      "interviewType": "TQ1",
      "candidateName": "Zella Willms",
      "talentRep": "joey-butta",
      "hidden": false,
      "startTime": 1652199300,
      "friendlyStartTime": "5/10/2022, 12:15:00 PM"
    },
    {
      "interviewType": "TQ1",
      "candidateName": "Lily Price",
      "talentRep": "tali-runs",
      "hidden": false,
      "startTime": 1652804100,
      "friendlyStartTime": "5/17/2022, 12:15:00 PM"
    },
    {
      "interviewType": "TQ1",
      "candidateName": "Jazmyn Powlowski",
      "talentRep": "bearded-jesus",
      "hidden": true,
      "startTime": 1653408900,
      "friendlyStartTime": "5/24/2022, 12:15:00 PM"
    },
    {
      "interviewType": "TQ1",
      "candidateName": "Pasquale Tromp",
      "talentRep": "lan-party-man",
      "hidden": true,
      "startTime": 1654013700,
      "friendlyStartTime": "5/31/2022, 12:15:00 PM"
    },
    {
      "interviewType": "TQ1",
      "candidateName": "Daphnee Weissnat",
      "talentRep": "joey-butta",
      "hidden": false,
      "startTime": 1654618500,
      "friendlyStartTime": "6/7/2022, 12:15:00 PM"
    },
    {
      "interviewType": "TQ1",
      "candidateName": "Minnie Herman",
      "talentRep": "hieu-hieu",
      "hidden": false,
      "startTime": 1655223300,
      "friendlyStartTime": "6/14/2022, 12:15:00 PM"
    },
    {
      "interviewType": "TQ1",
      "candidateName": "Dulce Gaylord",
      "talentRep": "hieu-hieu",
      "hidden": false,
      "startTime": 1655828100,
      "friendlyStartTime": "6/21/2022, 12:15:00 PM"
    },
    {
      "interviewType": "TQ1",
      "candidateName": "Violette Grady",
      "talentRep": "joey-butta",
      "hidden": false,
      "startTime": 1656432900,
      "friendlyStartTime": "6/28/2022, 12:15:00 PM"
    }
  ],
  "bernie-metz-usds": [
    {
      "interviewType": "TQ2",
      "candidateName": "Jalyn Wiegand",
      "talentRep": "tali-runs",
      "hidden": false,
      "startTime": 1652363100,
      "friendlyStartTime": "5/12/2022, 9:45:00 AM"
    },
    {
      "interviewType": "TQ1",
      "candidateName": "Roger Little",
      "talentRep": "bearded-jesus",
      "hidden": false,
      "startTime": 1652967900,
      "friendlyStartTime": "5/19/2022, 9:45:00 AM"
    },
    {
      "interviewType": "TQ2",
      "candidateName": "Virginia Gerhold",
      "talentRep": "lan-party-man",
      "hidden": false,
      "startTime": 1653572700,
      "friendlyStartTime": "5/26/2022, 9:45:00 AM"
    }
  ],
  "brionna-hilll-usds": [
    {
      "interviewType": "TQ2",
      "candidateName": "Newton Kirlin",
      "talentRep": "tali-runs",
      "hidden": false,
      "startTime": 1652391900,
      "friendlyStartTime": "5/12/2022, 5:45:00 PM"
    },
    {
      "interviewType": "TQ2",
      "candidateName": "Chris Becker",
      "talentRep": "ange-the-knife",
      "hidden": false,
      "startTime": 1652996700,
      "friendlyStartTime": "5/19/2022, 5:45:00 PM"
    },
    {
      "interviewType": "TQ2",
      "candidateName": "Ethel Kub",
      "talentRep": "joey-butta",
      "hidden": false,
      "startTime": 1653601500,
      "friendlyStartTime": "5/26/2022, 5:45:00 PM"
    },
    {
      "interviewType": "TQ2",
      "candidateName": "Rosalinda Denesik",
      "talentRep": "bearded-jesus",
      "hidden": false,
      "startTime": 1654206300,
      "friendlyStartTime": "6/2/2022, 5:45:00 PM"
    }
  ]
}